lilly/__init__.py
lilly/__main__.py
lilly/applications.py
lilly/conf.py
lilly/actions/__init__.py
lilly/actions/base.py
lilly/actions/crud.py
lilly/datasources/__init__.py
lilly/datasources/base.py
lilly/datasources/sqlalchemy.py
lilly/repositories/__init__.py
lilly/repositories/base.py
lilly/repositories/sqlalchemy.py
lilly/routing/__init__.py
lilly/routing/_base.py
lilly/routing/_crud.py
lilly/routing/_decorators.py
lilly/routing/_router.py
lilly/stubs/__init__.py
lilly/stubs/main.py
lilly/stubs/settings.py
lilly/stubs/service/__init__.py
lilly/stubs/service/actions.py
lilly/stubs/service/datasources.py
lilly/stubs/service/dtos.py
lilly/stubs/service/repositories.py
lilly/stubs/service/routes.py
test/assets/__init__.py
test/assets/mock_internals.py
test/assets/mock_settings.py
test/assets/mock_services/__init__.py
test/assets/mock_services/crud/__init__.py
test/assets/mock_services/crud/routes.py
test/assets/mock_services/first/__init__.py
test/assets/mock_services/first/dtos.py
test/assets/mock_services/first/routes.py
test/assets/mock_services/second/__init__.py
test/assets/mock_services/second/dtos.py
test/assets/mock_services/second/routes.py
test/test_actions/__init__.py
test/test_actions/test_base.py
test/test_actions/test_crud.py
test/test_datasources/__init__.py
test/test_datasources/test_sqlalchemy.py
test/test_repositories/__init__.py
test/test_repositories/test_base.py
test/test_repositories/test_sqlalchemy.py
test/test_routing/__init__.py
test/test_routing/test_base.py
test/test_routing/test_crud.py
lilly-0.3.0.dist-info/LICENSE
lilly-0.3.0.dist-info/METADATA
lilly-0.3.0.dist-info/WHEEL
lilly-0.3.0.dist-info/top_level.txt
lilly-0.3.0.dist-info/RECORD
