Metadata-Version: 2.1
Name: lilly
Version: 0.3.0
Summary: This package provides an opinionated SOA-layered fastapi-based web-framework.
Home-page: https://github.com/sopherapps/lilly
Author: Martin Ahindura
Author-email: team.sopherapps@gmail.com
License: MIT
Platform: UNKNOWN
Classifier: License :: OSI Approved :: MIT License
Classifier: Programming Language :: Python :: 3
Classifier: Programming Language :: Python :: 3.7
License-File: LICENSE
Requires-Dist: fastapi
Requires-Dist: click
Requires-Dist: pydantic
Requires-Dist: fastapi-utils
Requires-Dist: SQLAlchemy
